django_ultracache-2.3.dist-info/licenses/AUTHORS.rst
django_ultracache-2.3.dist-info/licenses/LICENSE
ultracache/__init__.py
ultracache/apps.py
ultracache/decorators.py
ultracache/middleware.py
ultracache/models.py
ultracache/monkey.py
ultracache/purgers.py
ultracache/signals.py
ultracache/tasks.py
ultracache/utils.py
ultracache/__pycache__/__init__.cpython-311.pyc
ultracache/__pycache__/__init__.cpython-312.pyc
ultracache/__pycache__/__init__.cpython-38.pyc
ultracache/__pycache__/apps.cpython-311.pyc
ultracache/__pycache__/apps.cpython-312.pyc
ultracache/__pycache__/apps.cpython-38.pyc
ultracache/__pycache__/decorators.cpython-311.pyc
ultracache/__pycache__/decorators.cpython-312.pyc
ultracache/__pycache__/decorators.cpython-38.pyc
ultracache/__pycache__/middleware.cpython-311.pyc
ultracache/__pycache__/middleware.cpython-312.pyc
ultracache/__pycache__/middleware.cpython-38.pyc
ultracache/__pycache__/models.cpython-311.pyc
ultracache/__pycache__/models.cpython-312.pyc
ultracache/__pycache__/models.cpython-38.pyc
ultracache/__pycache__/monkey.cpython-311.pyc
ultracache/__pycache__/monkey.cpython-312.pyc
ultracache/__pycache__/monkey.cpython-38.pyc
ultracache/__pycache__/signals.cpython-311.pyc
ultracache/__pycache__/signals.cpython-312.pyc
ultracache/__pycache__/signals.cpython-38.pyc
ultracache/__pycache__/tasks.cpython-311.pyc
ultracache/__pycache__/tasks.cpython-312.pyc
ultracache/__pycache__/tasks.cpython-38.pyc
ultracache/__pycache__/utils.cpython-311.pyc
ultracache/__pycache__/utils.cpython-312.pyc
ultracache/__pycache__/utils.cpython-38.pyc
ultracache/templatetags/__init__.py
ultracache/templatetags/ultracache_tags.py
ultracache/templatetags/ultracache_test_tags.py
ultracache/templatetags/__pycache__/__init__.cpython-311.pyc
ultracache/templatetags/__pycache__/__init__.cpython-312.pyc
ultracache/templatetags/__pycache__/__init__.cpython-38.pyc
ultracache/templatetags/__pycache__/ultracache_tags.cpython-311.pyc
ultracache/templatetags/__pycache__/ultracache_tags.cpython-312.pyc
ultracache/templatetags/__pycache__/ultracache_tags.cpython-38.pyc
django_ultracache-2.3.dist-info/METADATA
django_ultracache-2.3.dist-info/WHEEL
django_ultracache-2.3.dist-info/top_level.txt
django_ultracache-2.3.dist-info/RECORD
