Metadata-Version: 2.4
Name: django-ultracache
Version: 2.3
Summary: Cache views, template fragments and arbitrary Python code. Monitor Django object changes to perform automatic fine-grained cache invalidation from Django level, through proxies, to the browser. Make Django really fast.
Home-page: http://github.com/hedleyroos/django-ultracache
Author: Hedley Roos
Author-email: hedleyroos@gmail.com
License: BSD
Classifier: Programming Language :: Python
Classifier: License :: OSI Approved :: BSD License
Classifier: Operating System :: OS Independent
Classifier: Framework :: Django
Classifier: Intended Audience :: Developers
Classifier: Topic :: Internet :: WWW/HTTP :: Dynamic Content
License-File: LICENSE
License-File: AUTHORS.rst
Dynamic: author
Dynamic: author-email
Dynamic: classifier
Dynamic: description
Dynamic: description-content-type
Dynamic: home-page
Dynamic: license
Dynamic: license-file
Dynamic: summary
